DSA/__init__.py
DSA/dmd.py
DSA/dsa.py
DSA/excess.py
DSA/kerneldmd.py
DSA/simdist.py
DSA/stats.py
dsa_metric-1.0.2.dist-info/licenses/LICENSE
dsa_metric-1.0.2.dist-info/METADATA
dsa_metric-1.0.2.dist-info/WHEEL
dsa_metric-1.0.2.dist-info/top_level.txt
dsa_metric-1.0.2.dist-info/RECORD
