Metadata-Version: 2.4
Name: dsa-metric
Version: 1.0.2
Summary: Dynamical Similarity Analysis
Home-page: https://github.com/mitchellostrow/DSA
Author: Mitchell Ostrow
Author-email: Mitchell Ostrow <ostrow@mit.edu>
License-Expression: MIT
Project-URL: Homepage, https://github.com/mitchellostrow/DSA
Project-URL: Issues, https://github.com/mitchellostrow/DSA/issues
Classifier: Programming Language :: Python :: 3
Classifier: Operating System :: OS Independent
Requires-Python: >=3.9
License-File: LICENSE
Dynamic: author
Dynamic: home-page
Dynamic: license-file
